gmcomp/__init__.py
gmcomp/gmcomp.py
gmcomp-0.0.2.dist-info/licenses/LICENSE
gmcomp-0.0.2.dist-info/METADATA
gmcomp-0.0.2.dist-info/WHEEL
gmcomp-0.0.2.dist-info/entry_points.txt
gmcomp-0.0.2.dist-info/top_level.txt
gmcomp-0.0.2.dist-info/RECORD
